authentication/__init__.py
authentication/admin.py
authentication/apps.py
authentication/auth.py
authentication/factories.py
authentication/helper.py
authentication/models.py
authentication/repositories.py
authentication/serializers.py
authentication/services.py
authentication/urls.py
authentication/validators.py
authentication/views.py
authentication/templates/__init__.py
authentication/templates/authentication/__init__.py
authentication/templates/authentication/mail_reset_passwd.html
authentication/templates/authentication/mail_reset_passwd.txt
authentication/templates/authentication/mail_verify.html
authentication/templates/authentication/mail_verify.txt
django_generic_token_authentication-0.8.6.data/data/templates/mail_reset_passwd.html
django_generic_token_authentication-0.8.6.data/data/templates/mail_reset_passwd.txt
django_generic_token_authentication-0.8.6.data/data/templates/mail_verify.html
django_generic_token_authentication-0.8.6.data/data/templates/mail_verify.txt
tests/__init__.py
tests/models.py
tests/serializers.py
tests/test_settings.py
tests/tests.py
django_generic_token_authentication-0.8.6.dist-info/LICENSE
django_generic_token_authentication-0.8.6.dist-info/METADATA
django_generic_token_authentication-0.8.6.dist-info/WHEEL
django_generic_token_authentication-0.8.6.dist-info/top_level.txt
django_generic_token_authentication-0.8.6.dist-info/RECORD
